Workbook

Sheet Read me
A1: Project Io — Economy Tuning Model
A3: Interactive model of the Layer 3 economy: extraction & processing profitability and market-clearing price resolution. Change the blue cells to explore tunings; every black cell recalculates.
A7: Colour legend
A8: Blue text | B8: Inputs / assumptions you change
A9: Black text | B9: Formulas (do not edit)
A10: Green text | B10: Links pulling from the Constants sheet
A12: Tabs
A13: Constants | B13: Base prices, building economics, thresholds, price-band parameters. The single source of truth.
A14: Recipes | B14: The three Layer 3 processing recipes and their per-unit value-add.
A15: Extraction P&L | B15: Per-tick profit of an extraction site by resource — richness, workforce, hazard.
A16: Processing P&L | B16: Per-tick profit of a processing facility by recipe — workforce, input/output prices.
A17: Market price band | B17: Supply/demand → resolved price, using the in-engine sqrt model and clamp.
A20: Source: docs/economy/RESOURCES.md & PRODUCTION.md; scripts/recipes.lua & economy.lua; src/world/hard_coded_world.cpp (base prices); src/world/market_clearing.cpp (price band). As of v0.0.4, 2026-06-15.

Sheet Constants
A1: Constants
A2: Edit blue cells to re-tune. Other sheets reference these.
A3: Resource | B3: Tier | C3: Base price ($/unit) | D3: Extraction building
A4: iron_ore | B4: 1 | C4: 2.5 | D4: Mine
A5: petroleum | B5: 1 | C5: 3.5 | D5: Oil Platform
A6: water | B6: 1 | C6: 1.5 | D6: Ice Extractor
A7: agricultural_produce | B7: 1 | C7: 3 | D7: Farm
A8: steel | B8: 2 | C8: 8 | D8: (Smelter)
A9: refined_fuel | B9: 2 | C9: 10 | D9: (Refinery)
A10: food_rations | B10: 2 | C10: 6 | D10: (Food Processor)
A12: Building economics (per tick unless noted)
A13: Building type | B13: base_rate | C13: maintenance ($) | D13: base_wage ($) | E13: build_cost ($)
A14: extraction_site | B14: 20 | C14: 5 | D14: 8 | E14: 100 | G14: base_rate: extraction = units/tick at richness 1, workforce 1; processing = batches/tick at workforce 1
A15: processing_facility | B15: 8 | C15: 10 | D15: 12 | E15: 200
A16: port | B16: 0 | C16: 8 | D16: 6 | E16: 150
A18: Thresholds & price band
A19: Parameter | B19: Value | C19: Note
A20: t_full | B20: 1 | C20: pool coverage >= this -> run full from pool
A21: t_idle | B21: 0.2 | C21: coverage below this -> building idles
A22: price_floor_mult | B22: 0.25 | C22: lowest price = this x base
A23: price_ceil_mult | B23: 4 | C23: highest price = this x base
A24: price_smoothing | B24: 0.5 | C24: EMA factor toward tick target (not modelled per-tick here)

Sheet Recipes
A1: Processing recipes
A2: Per-batch conversion (recipes.lua). Value-add = output value minus input value, per batch.
A4: Recipe (id) | B4: Input | C4: In qty | D4: Output | E4: Out qty | F4: Input $/u | G4: Output $/u | H4: Input value | I4: Output value | J4: Value-add / batch | K4: Value-add ratio
A5: steel (0) | B5: iron_ore | C5: 2 | D5: steel | E5: 1 | F5: =VLOOKUP(B5,Constants!$A$4:$C$10,3,FALSE()) -> 2.5 | G5: =VLOOKUP(D5,Constants!$A$4:$C$10,3,FALSE()) -> 8 | H5: =C5*F5 -> 5 | I5: =E5*G5 -> 8 | J5: =I5-H5 -> 3 | K5: =IF(H5=0,"-",I5/H5) -> 1.6
A6: refined_fuel (1) | B6: petroleum | C6: 2 | D6: refined_fuel | E6: 1 | F6: =VLOOKUP(B6,Constants!$A$4:$C$10,3,FALSE()) -> 3.5 | G6: =VLOOKUP(D6,Constants!$A$4:$C$10,3,FALSE()) -> 10 | H6: =C6*F6 -> 7 | I6: =E6*G6 -> 10 | J6: =I6-H6 -> 3 | K6: =IF(H6=0,"-",I6/H6) -> 1.4285714
A7: food_rations (2) | B7: agricultural_produce | C7: 2 | D7: food_rations | E7: 1 | F7: =VLOOKUP(B7,Constants!$A$4:$C$10,3,FALSE()) -> 3 | G7: =VLOOKUP(D7,Constants!$A$4:$C$10,3,FALSE()) -> 6 | H7: =C7*F7 -> 6 | I7: =E7*G7 -> 6 | J7: =I7-H7 -> 0 | K7: =IF(H7=0,"-",I7/H7) -> 1

Sheet Extraction P&L
A1: Extraction P&L (per tick)
A2: output = base_rate x richness x workforce x (1 - hazard). Change richness / workforce / hazard (blue).
A4: Resource | B4: Richness | C4: Workforce | D4: Hazard | E4: Price $/u | F4: Output/tick | G4: Revenue | H4: Wage | I4: Maintenance | J4: Net / tick | K4: Payback (ticks)
A5: iron_ore | B5: 1 | C5: 1 | D5: 0.1 | E5: =VLOOKUP(A5,Constants!$A$4:$C$10,3,FALSE()) -> 2.5 | F5: =Constants!$B$14*B5*C5*(1-D5) -> 18 | G5: =F5*E5 -> 45 | H5: =C5*Constants!$D$14 -> 8 | I5: =Constants!$C$14 -> 5 | J5: =G5-H5-I5 -> 32 | K5: =IF(J5<=0,"never",Constants!$E$14/J5) -> 3.125
A6: petroleum | B6: 1 | C6: 1 | D6: 0.15 | E6: =VLOOKUP(A6,Constants!$A$4:$C$10,3,FALSE()) -> 3.5 | F6: =Constants!$B$14*B6*C6*(1-D6) -> 17 | G6: =F6*E6 -> 59.5 | H6: =C6*Constants!$D$14 -> 8 | I6: =Constants!$C$14 -> 5 | J6: =G6-H6-I6 -> 46.5 | K6: =IF(J6<=0,"never",Constants!$E$14/J6) -> 2.1505376
A7: water | B7: 1 | C7: 1 | D7: 0.1 | E7: =VLOOKUP(A7,Constants!$A$4:$C$10,3,FALSE()) -> 1.5 | F7: =Constants!$B$14*B7*C7*(1-D7) -> 18 | G7: =F7*E7 -> 27 | H7: =C7*Constants!$D$14 -> 8 | I7: =Constants!$C$14 -> 5 | J7: =G7-H7-I7 -> 14 | K7: =IF(J7<=0,"never",Constants!$E$14/J7) -> 7.1428571
A8: agricultural_produce | B8: 1 | C8: 1 | D8: 0.05 | E8: =VLOOKUP(A8,Constants!$A$4:$C$10,3,FALSE()) -> 3 | F8: =Constants!$B$14*B8*C8*(1-D8) -> 19 | G8: =F8*E8 -> 57 | H8: =C8*Constants!$D$14 -> 8 | I8: =Constants!$C$14 -> 5 | J8: =G8-H8-I8 -> 44 | K8: =IF(J8<=0,"never",Constants!$E$14/J8) -> 2.2727273

Sheet Processing P&L
A1: Processing P&L (per tick)
A2: batches = base_rate x workforce. Inputs auto-bought at market price if not self-supplied. Change workforce (blue); prices link to Constants.
A4: Recipe | B4: Workforce | C4: Batches | D4: Input | E4: In $/u | F4: Out $/u | G4: Input cost | H4: Revenue | I4: Wage | J4: Maintenance | K4: Net / tick | L4: Payback (ticks)
A5: =Recipes!A5 -> steel (0) | B5: 1 | C5: =Constants!$B$15*B5 -> 8 | D5: =Recipes!B5 -> iron_ore | E5: =Recipes!F5 -> 2.5 | F5: =Recipes!G5 -> 8 | G5: =C5*Recipes!C5*E5 -> 40 | H5: =C5*Recipes!E5*F5 -> 64 | I5: =B5*Constants!$D$15 -> 12 | J5: =Constants!$C$15 -> 10 | K5: =H5-G5-I5-J5 -> 2 | L5: =IF(K5<=0,"never",Constants!$E$15/K5) -> 100
A6: =Recipes!A6 -> refined_fuel (1) | B6: 1 | C6: =Constants!$B$15*B6 -> 8 | D6: =Recipes!B6 -> petroleum | E6: =Recipes!F6 -> 3.5 | F6: =Recipes!G6 -> 10 | G6: =C6*Recipes!C6*E6 -> 56 | H6: =C6*Recipes!E6*F6 -> 80 | I6: =B6*Constants!$D$15 -> 12 | J6: =Constants!$C$15 -> 10 | K6: =H6-G6-I6-J6 -> 2 | L6: =IF(K6<=0,"never",Constants!$E$15/K6) -> 100
A7: =Recipes!A7 -> food_rations (2) | B7: 1 | C7: =Constants!$B$15*B7 -> 8 | D7: =Recipes!B7 -> agricultural_produce | E7: =Recipes!F7 -> 3 | F7: =Recipes!G7 -> 6 | G7: =C7*Recipes!C7*E7 -> 48 | H7: =C7*Recipes!E7*F7 -> 48 | I7: =B7*Constants!$D$15 -> 12 | J7: =Constants!$C$15 -> 10 | K7: =H7-G7-I7-J7 -> -22 | L7: =IF(K7<=0,"never",Constants!$E$15/K7) -> never
A9: Note: input cost assumes 100% auto-buy at market. If the recipe's raw input is self-supplied from your own extraction, treat input cost as 0 and read net as gross margin before logistics.

Sheet Market price band
A1: Market price resolution
A2: Engine model: target = base x sqrt(demand/supply), clamped to [floor x base, ceil x base]. Demand with zero supply pins to the ceiling. Change supply/demand (blue).
A5: Resource | B5: Base $ | C5: Supply | D5: Demand | E5: D/S ratio | F5: Raw target | G5: Floor | H5: Ceiling | I5: Resolved price | J5: x base
A6: iron_ore | B6: =VLOOKUP(A6,Constants!$A$4:$C$10,3,FALSE()) -> 2.5 | C6: 100 | D6: 100 | E6: =IF(C6=0,"inf",D6/C6) -> 1 | F6: =IF(C6=0,IF(D6>0,B6*Constants!$B$23,B6),B6*SQRT(D6/C6)) -> 2.5 | G6: =B6*Constants!$B$22 -> 0.625 | H6: =B6*Constants!$B$23 -> 10 | I6: =MIN(MAX(F6,G6),H6) -> 2.5 | J6: =I6/B6 -> 1
A7: petroleum | B7: =VLOOKUP(A7,Constants!$A$4:$C$10,3,FALSE()) -> 3.5 | C7: 80 | D7: 120 | E7: =IF(C7=0,"inf",D7/C7) -> 1.5 | F7: =IF(C7=0,IF(D7>0,B7*Constants!$B$23,B7),B7*SQRT(D7/C7)) -> 4.286607 | G7: =B7*Constants!$B$22 -> 0.875 | H7: =B7*Constants!$B$23 -> 14 | I7: =MIN(MAX(F7,G7),H7) -> 4.286607 | J7: =I7/B7 -> 1.2247449
A8: water | B8: =VLOOKUP(A8,Constants!$A$4:$C$10,3,FALSE()) -> 1.5 | C8: 150 | D8: 50 | E8: =IF(C8=0,"inf",D8/C8) -> 0.33333333 | F8: =IF(C8=0,IF(D8>0,B8*Constants!$B$23,B8),B8*SQRT(D8/C8)) -> 0.8660254 | G8: =B8*Constants!$B$22 -> 0.375 | H8: =B8*Constants!$B$23 -> 6 | I8: =MIN(MAX(F8,G8),H8) -> 0.8660254 | J8: =I8/B8 -> 0.57735027
A9: agricultural_produce | B9: =VLOOKUP(A9,Constants!$A$4:$C$10,3,FALSE()) -> 3 | C9: 100 | D9: 100 | E9: =IF(C9=0,"inf",D9/C9) -> 1 | F9: =IF(C9=0,IF(D9>0,B9*Constants!$B$23,B9),B9*SQRT(D9/C9)) -> 3 | G9: =B9*Constants!$B$22 -> 0.75 | H9: =B9*Constants!$B$23 -> 12 | I9: =MIN(MAX(F9,G9),H9) -> 3 | J9: =I9/B9 -> 1
A10: steel | B10: =VLOOKUP(A10,Constants!$A$4:$C$10,3,FALSE()) -> 8 | C10: 60 | D10: 90 | E10: =IF(C10=0,"inf",D10/C10) -> 1.5 | F10: =IF(C10=0,IF(D10>0,B10*Constants!$B$23,B10),B10*SQRT(D10/C10)) -> 9.797959 | G10: =B10*Constants!$B$22 -> 2 | H10: =B10*Constants!$B$23 -> 32 | I10: =MIN(MAX(F10,G10),H10) -> 9.797959 | J10: =I10/B10 -> 1.2247449
A11: refined_fuel | B11: =VLOOKUP(A11,Constants!$A$4:$C$10,3,FALSE()) -> 10 | C11: 40 | D11: 80 | E11: =IF(C11=0,"inf",D11/C11) -> 2 | F11: =IF(C11=0,IF(D11>0,B11*Constants!$B$23,B11),B11*SQRT(D11/C11)) -> 14.142136 | G11: =B11*Constants!$B$22 -> 2.5 | H11: =B11*Constants!$B$23 -> 40 | I11: =MIN(MAX(F11,G11),H11) -> 14.142136 | J11: =I11/B11 -> 1.4142136
A12: food_rations | B12: =VLOOKUP(A12,Constants!$A$4:$C$10,3,FALSE()) -> 6 | C12: 100 | D12: 40 | E12: =IF(C12=0,"inf",D12/C12) -> 0.4 | F12: =IF(C12=0,IF(D12>0,B12*Constants!$B$23,B12),B12*SQRT(D12/C12)) -> 3.7947332 | G12: =B12*Constants!$B$22 -> 1.5 | H12: =B12*Constants!$B$23 -> 24 | I12: =MIN(MAX(F12,G12),H12) -> 3.7947332 | J12: =I12/B12 -> 0.63245553
